.gitignore
INSTALL.md
LICENSE
NEWS.md
README.md
setup.py
doc/dbadmin.md
doc/rpi_lcd_ir_board.md
doc/rpi_lcd_ir_board.png
doc/rpi_lcd_ir_board.svg
doc/rpi_lcd_ir_board_components.png
doc/rpi_lcd_ir_board_crosswires.png
doc/rpi_lcd_ir_schematics.png
doc/rpi_lcd_ir_schematics.svg
doc/zeromq.md
etc/lirc/cyrus-commander.conf
etc/udev/rules.d/99-codplayer.rules
src/codadmin
src/codctl
src/codlcd
src/codlircd
src/codmousectl
src/codplayerd
src/codrestd
src/codplayer/__init__.py
src/codplayer/audio.py
src/codplayer/c_alsa_sink.c
src/codplayer/codaemon.py
src/codplayer/command.py
src/codplayer/config.py
src/codplayer/db.py
src/codplayer/lcd.py
src/codplayer/lirc.py
src/codplayer/model.py
src/codplayer/player.py
src/codplayer/py_alsa_sink.py
src/codplayer/remotecontrol.py
src/codplayer/rest.py
src/codplayer/rip.py
src/codplayer/serialize.py
src/codplayer/sink.py
src/codplayer/source.py
src/codplayer/state.py
src/codplayer/toc.py
src/codplayer/zerohub.py
src/codplayer.egg-info/PKG-INFO
src/codplayer.egg-info/SOURCES.txt
src/codplayer.egg-info/dependency_links.txt
src/codplayer.egg-info/eager_resources.txt
src/codplayer.egg-info/requires.txt
src/codplayer.egg-info/top_level.txt
src/codplayer/data/config/codlcd.conf
src/codplayer/data/config/codlircd.conf
src/codplayer/data/config/codmq.conf
src/codplayer/data/config/codplayer.conf
src/codplayer/data/config/codrest.conf
src/codplayer/data/dbadmin/.jshint-emacs.js
src/codplayer/data/dbadmin/.jshintrc
src/codplayer/data/dbadmin/Makefile
src/codplayer/data/dbadmin/cod-symbols.woff
src/codplayer/data/dbadmin/codadmin.css
src/codplayer/data/dbadmin/codadmin.html
src/codplayer/data/dbadmin/codadmin.js
src/codplayer/data/dbadmin/fonts/glyphicons-halflings-regular.woff
src/codplayer/data/dbadmin/fonts/glyphicons-halflings-regular.woff2
src/codplayer/data/dbadmin/libs/backbone-min.js
src/codplayer/data/dbadmin/libs/backbone.js
src/codplayer/data/dbadmin/libs/bootstrap-theme.min.css
src/codplayer/data/dbadmin/libs/bootstrap.min.css
src/codplayer/data/dbadmin/libs/bootstrap.min.js
src/codplayer/data/dbadmin/libs/jquery-2.0.3.min.js
src/codplayer/data/dbadmin/libs/underscore-min.js
src/codplayer/test/__init__.py
src/codplayer/test/test_audio.py
