Metadata-Version: 1.0
Name: codplayer
Version: 2.0
Summary: Complicated CD player
Home-page: https://github.com/petli/codplayer
Author: Peter Liljenberg
Author-email: peter.liljenberg@gmail.com
License: MIT
Keywords: cd cdparanoia cdrdao cdplayer
Platform: UNKNOWN
